{
  "collectionName": "components_layout_report_sections",
  "info": {
    "displayName": "Report Section",
    "description": ""
  },
  "options": {},
  "attributes": {
    "Title": {
      "type": "string"
    },
    "Subtitle": {
      "type": "string"
    },
    "Blurb": {
      "type": "text"
    },
    "ImageRight": {
      "type": "media",
      "multiple": false,
      "required": false,
      "allowedTypes": [
        "images",
        "files",
        "videos",
        "audios"
      ]
    },
    "ContentLeft": {
      "type": "richtext"
    },
    "Type": {
      "type": "enumeration",
      "enum": [
        "singleImage",
        "doubleImage"
      ],
      "default": "singleImage"
    },
    "imageLeft": {
      "allowedTypes": [
        "images",
        "files",
        "videos",
        "audios"
      ],
      "type": "media",
      "multiple": false
    }
  }
}
